tree_aid/__init__.py
tree_aid/placettes.py
tree_aid/placettes_utils.py
tree_aid/data/.DS_Store
tree_aid/data/wd_means.csv
tree_aid/data/E/E.bil
tree_aid/data/E/E.bil.aux.xml
tree_aid/data/E/E.hdr
tree_aid/data/E/E.prj
tree_aid-0.0.3.dist-info/LICENSE
tree_aid-0.0.3.dist-info/METADATA
tree_aid-0.0.3.dist-info/WHEEL
tree_aid-0.0.3.dist-info/top_level.txt
tree_aid-0.0.3.dist-info/RECORD
