Metadata-Version: 2.1
Name: tree-aid
Version: 0.0.3
Summary: ETL tools for Tree Aid
Home-page: https://github.com/charliehpearce/tree_aid_test
Author: 180DC Bristol
Author-email: sv20666@bristol.ac.uk
License: UNKNOWN
Project-URL: Bug Tracker, https://github.com/charliehpearce/tree_aid_test/issues
Platform: UNKNOWN
Classifier: Programming Language :: Python :: 3
Classifier: License :: OSI Approved :: MIT License
Classifier: Operating System :: OS Independent
Requires-Python: >=3.6
License-File: LICENSE
Requires-Dist: pandas (>=1.2.0)
Requires-Dist: rasterio (>=1.2.0)
